SsyiWorking
