Metadata-Version: 1.0
Name: SsyiWorking
Version: 0.3
Summary: This is a demo framework
Home-page: http://www.sys-test.com.cn
Author: Ssyi
Author-email: shensongyi@sys-test.com.cn
License: MIT
Platform: UNKNOWN
